odoo/addons/server_env_ebill_paynet/README.rst
odoo/addons/server_env_ebill_paynet/__init__.py
odoo/addons/server_env_ebill_paynet/__manifest__.py
odoo/addons/server_env_ebill_paynet/i18n/server_env_ebill_paynet.pot
odoo/addons/server_env_ebill_paynet/models/__init__.py
odoo/addons/server_env_ebill_paynet/models/paynet_service.py
odoo/addons/server_env_ebill_paynet/readme/CONTRIBUTORS.rst
odoo/addons/server_env_ebill_paynet/readme/DESCRIPTION.rst
odoo/addons/server_env_ebill_paynet/static/description/icon.png
odoo/addons/server_env_ebill_paynet/static/description/index.html
odoo13_addon_server_env_ebill_paynet-13.0.1.0.1.dist-info/METADATA
odoo13_addon_server_env_ebill_paynet-13.0.1.0.1.dist-info/WHEEL
odoo13_addon_server_env_ebill_paynet-13.0.1.0.1.dist-info/top_level.txt
odoo13_addon_server_env_ebill_paynet-13.0.1.0.1.dist-info/RECORD
